veeam_br/.gitignore
veeam_br/README.md
veeam_br/pyproject.toml
veeam_br/v1_3_rev1/__init__.py
veeam_br/v1_3_rev1/client.py
veeam_br/v1_3_rev1/errors.py
veeam_br/v1_3_rev1/py.typed
veeam_br/v1_3_rev1/types.py
veeam_br/v1_3_rev1/api/__init__.py
veeam_br/v1_3_rev1/api/active_directory_domains/__init__.py
veeam_br/v1_3_rev1/api/active_directory_domains/create_ad_domain.py
veeam_br/v1_3_rev1/api/active_directory_domains/delete_ad_domain.py
veeam_br/v1_3_rev1/api/active_directory_domains/get_ad_domain.py
veeam_br/v1_3_rev1/api/active_directory_domains/get_all_ad_domains.py
veeam_br/v1_3_rev1/api/agents/__init__.py
veeam_br/v1_3_rev1/api/agents/create_computer_recovery_token.py
veeam_br/v1_3_rev1/api/agents/create_protection_group.py
veeam_br/v1_3_rev1/api/agents/create_recovery_media_for_discovered_entity.py
veeam_br/v1_3_rev1/api/agents/delete_computer_recovery_token.py
veeam_br/v1_3_rev1/api/agents/delete_discovered_entity.py
veeam_br/v1_3_rev1/api/agents/delete_protection_group.py
veeam_br/v1_3_rev1/api/agents/disable_protection_group.py
veeam_br/v1_3_rev1/api/agents/download_protection_group_packages.py
veeam_br/v1_3_rev1/api/agents/enable_protection_group.py
veeam_br/v1_3_rev1/api/agents/get_all_agent_packages.py
veeam_br/v1_3_rev1/api/agents/get_all_agent_packages_for_unix.py
veeam_br/v1_3_rev1/api/agents/get_all_computer_recovery_tokens.py
veeam_br/v1_3_rev1/api/agents/get_all_protection_groups.py
veeam_br/v1_3_rev1/api/agents/get_computer_recovery_token.py
veeam_br/v1_3_rev1/api/agents/get_discovered_entities.py
veeam_br/v1_3_rev1/api/agents/get_discovered_entity.py
veeam_br/v1_3_rev1/api/agents/get_protected_computer.py
veeam_br/v1_3_rev1/api/agents/get_protected_computers.py
veeam_br/v1_3_rev1/api/agents/get_protection_group.py
veeam_br/v1_3_rev1/api/agents/install_agent_on_discovered_entities.py
veeam_br/v1_3_rev1/api/agents/install_cbt_driver_on_discovered_entities.py
veeam_br/v1_3_rev1/api/agents/rescan_discovered_entities.py
veeam_br-0.1.0b1.dist-info/licenses/LICENSE
veeam_br-0.1.0b1.dist-info/METADATA
veeam_br-0.1.0b1.dist-info/WHEEL
veeam_br-0.1.0b1.dist-info/top_level.txt
veeam_br-0.1.0b1.dist-info/RECORD
