Metadata-Version: 2.4
Name: veeam-br
Version: 0.1.0b1
Summary: Veeam Backup & Replication REST API wrapper for Python
Author-email: Jonah May <jonah@mayfamily.me>
License: Apache-2.0
Project-URL: Homepage, https://github.com/Cenvora/veeam-br
Project-URL: Repository, https://github.com/Cenvora/veeam-br
Project-URL: Documentation, https://github.com/Cenvora/veeam-br#readme
Classifier: Development Status :: 4 - Beta
Classifier: Intended Audience :: Developers
Classifier: Topic :: Software Development :: Libraries :: Python Modules
Classifier: License :: OSI Approved :: Apache Software License
Classifier: Programming Language :: Python :: 3
Classifier: Programming Language :: Python :: 3.8
Classifier: Operating System :: OS Independent
Requires-Python: >=3.8
License-File: LICENSE
Requires-Dist: httpx>=0.24.0
Requires-Dist: pydantic>=1.10.0
Provides-Extra: dev
Requires-Dist: pytest>=7.0.0; extra == "dev"
Requires-Dist: pytest-cov; extra == "dev"
Requires-Dist: black; extra == "dev"
Requires-Dist: ruff; extra == "dev"
Requires-Dist: pre-commit; extra == "dev"
Dynamic: license-file
